bugprint/__init__.py
bugprint/example_usage.py
bugprint/funcs.py
bugprint/bugprint/__init__.py
bugprint/bugprint/bp.py
bugprint-0.3.3.dist-info/LICENSE
bugprint-0.3.3.dist-info/METADATA
bugprint-0.3.3.dist-info/WHEEL
bugprint-0.3.3.dist-info/top_level.txt
bugprint-0.3.3.dist-info/RECORD
