Metadata-Version: 2.1
Name: bugprint
Version: 0.3.3
Summary: Debug printing made easy.
Home-page: https://github.com/erikluu/bugprint
Author: Erik Luu
Author-email: eeluu19@gmail.com
License: MIT
Keywords: python,debug,print
Classifier: Intended Audience :: Developers
Classifier: Programming Language :: Python :: 3
Classifier: Operating System :: Unix
Classifier: Operating System :: MacOS :: MacOS X
Classifier: Operating System :: Microsoft :: Windows
License-File: LICENSE
